cleaning_utils/__init__.py
cleaning_utils/address_cleaner.py
cleaning_utils/clear_stop_char.py
cleaning_utils/constants.py
cleaning_utils/datetime_diff.py
cleaning_utils/from_datetime_to_iso.py
cleaning_utils/from_dict_to_iso.py
cleaning_utils/from_khayyam_to_iso.py
cleaning_utils/human_number.py
cleaning_utils/number_separator.py
cleaning_utils/py.typed
cleaning_utils/remove_duplicate_words.py
cleaning_utils/replace_arabic_char.py
cleaning_utils/replace_stop_words.py
cleaning_utils/space_cleaner.py
cleaning_utils/to_fa_numbers.py
cleaning_utils/to_iso_datetime.py
cleaning_utils/types.py
cleaning_utils-0.1.5.dist-info/LICENSE
cleaning_utils-0.1.5.dist-info/WHEEL
cleaning_utils-0.1.5.dist-info/METADATA
cleaning_utils-0.1.5.dist-info/RECORD
