Metadata-Version: 2.1
Name: cleaning-utils
Version: 0.1.5
Summary: cleaning-utils is a collection of small Python functions and classes for formatting persian texts.
Home-page: https://github.com/rezashabrang/cleaning-utils
License: MIT
Author: aasaam
Author-email: beygi.ma@iums.ac.ir
Requires-Python: >=3.8,<4.0
Classifier: Development Status :: 3 - Alpha
Classifier: Intended Audience :: Developers
Classifier: License :: OSI Approved :: MIT License
Classifier: Operating System :: OS Independent
Classifier: Programming Language :: Python :: 3
Classifier: Programming Language :: Python :: 3.10
Classifier: Programming Language :: Python :: 3.8
Classifier: Programming Language :: Python :: 3.9
Classifier: Topic :: Software Development :: Libraries :: Python Modules
Requires-Dist: datetime
Requires-Dist: importlib_metadata (>=4.5.0,<5.0.0); python_version < "3.7"
Requires-Dist: khayyam
Requires-Dist: numpy (>=1.22.0,<2.0.0)
Requires-Dist: pandas
Requires-Dist: python-dateutil
Requires-Dist: pytz
Requires-Dist: urllib3 (>=1.26.4,<2.0.0)
Project-URL: Repository, https://github.com/rezashabrang/cleaning-utils
